django_frog-2.3.0.dist-info/DESCRIPTION.rst
django_frog-2.3.0.dist-info/METADATA
django_frog-2.3.0.dist-info/RECORD
django_frog-2.3.0.dist-info/WHEEL
django_frog-2.3.0.dist-info/entry_points.txt
django_frog-2.3.0.dist-info/metadata.json
django_frog-2.3.0.dist-info/top_level.txt
frog/__init__.py
frog/__version__.py
frog/admin.py
frog/auth.py
frog/auth_ldap.py
frog/cli.py
frog/common.py
frog/models.py
frog/plugin.py
frog/search_indexes.py
frog/send_file.py
frog/tests.py
frog/uploader.py
frog/urls.py
frog/video_thread.py
frog/fixtures/initial_data.json
frog/management/__init__.py
frog/management/commands/__init__.py
frog/management/commands/batch_import.py
frog/management/commands/frog_cron_tagless.py
frog/management/commands/frog_queue_videos.py
frog/management/commands/frog_thumbnails.py
frog/management/commands/frog_update_email.py
frog/management/commands/frog_watch.py
frog/management/commands/list_users.py
frog/management/commands/set_password.py
frog/management/commands/video_worker.py
frog/migrations/0001_initial.py
frog/migrations/0002_auto_20150908_1826.py
frog/migrations/0003_auto_20160809_2054.py
frog/migrations/0004_auto_20160809_2117.py
frog/migrations/0005_video_poster.py
frog/migrations/0006_video_framerate.py
frog/migrations/0007_auto_20161004_2333.py
frog/migrations/0008_auto_20170208_2107.py
frog/migrations/0009_auto_20170707_2218.py
frog/migrations/0010_remove_like_site.py
frog/migrations/0011_auto_20171210_1008.py
frog/migrations/__init__.py
frog/ng/3rdpartylicenses.txt
frog/ng/index.html
frog/ng/inline.4fbc71e24b5a2c054e7a.bundle.js
frog/ng/inline.d9fe3b75166907c7dc30.bundle.js
frog/ng/inline.dbe5ea475047bb28f1d5.bundle.js
frog/ng/main.2716826ceb158679be68.bundle.js
frog/ng/main.39e9a6948397463d1e05.bundle.js
frog/ng/main.96ca4af266978fcb8f2f.bundle.js
frog/ng/scripts.14d235a6d5a094a07744.bundle.js
frog/ng/scripts.440163de2935b6491a36.bundle.js
frog/ng/scripts.75e01057c781b829af1d.bundle.js
frog/ng/styles.98b23a368413c1acffb9.bundle.css
frog/ng/styles.c66768f70349c661e3c5.bundle.css
frog/ng/vendor.18aae68463deb2eb9e61.bundle.js
frog/ng/vendor.a0486f802a543ef06244.bundle.js
frog/ng/public/Thumbs.db
frog/ng/public/frog.png
frog/ng/public/pixel.png
