Metadata-Version: 2.0
Name: django-frog
Version: 2.3.0
Summary: Media server built on django
Home-page: https://github.com/theiviaxx/frog
Author: Brett Dixon
Author-email: theiviaxx@gmail.com
License: MIT
Platform: UNKNOWN
Classifier: Environment :: Web Environment
Classifier: Framework :: Django
Classifier: Intended Audience :: Developers
Classifier: License :: OSI Approved :: MIT License
Classifier: Natural Language :: English
Classifier: Programming Language :: Python
Requires-Dist: Django (==1.10)
Requires-Dist: Pillow (==4.3.0)
Requires-Dist: django-contrib-comments (==1.8.0)
Requires-Dist: django-haystack (==2.5.1)
Requires-Dist: path.py (==8.1.2)
Requires-Dist: psd-tools (==1.4)
Requires-Dist: pytz (==2015.2)
Requires-Dist: six (==1.9.0)
Requires-Dist: urllib3 (==1.10.2)
